ggpt/__init__.py
ggpt/__main__.py
ggpt/cli.py
ggpt/console.py
ggpt/const.py
ggpt/exception.py
ggpt/ggpt.py
ggpt/gpt.py
ggpt/utils.py
ggpt-0.2.0.dist-info/LICENSE.md
ggpt-0.2.0.dist-info/METADATA
ggpt-0.2.0.dist-info/WHEEL
ggpt-0.2.0.dist-info/entry_points.txt
ggpt-0.2.0.dist-info/RECORD
