Metadata-Version: 2.1
Name: ggpt
Version: 0.2.0
Summary: Gorgeous CLI tools using GPT
Home-page: https://github.com/jenz0000/ggpt
Author: jenz0000
Author-email: fullswing0603@gmail.com
Requires-Python: >=3.7.1,<4.0.0
Classifier: Programming Language :: Python :: 3
Classifier: Programming Language :: Python :: 3.8
Classifier: Programming Language :: Python :: 3.9
Classifier: Programming Language :: Python :: 3.10
Classifier: Programming Language :: Python :: 3.11
Classifier: Programming Language :: Python :: 3.12
Requires-Dist: click (>=8.1.3,<9.0.0)
Requires-Dist: openai (>=1.9.0,<2.0.0)
Requires-Dist: rich (>=13.3.2,<14.0.0)
Project-URL: Repository, https://github.com/jenz0000/ggpt
